Workbook

Sheet Summary
A1: K-G Portfolio Analysis — Kollen Glynn
A2: Sources: Fidelity Individual TOD statement Jul 2026; Fidelity Self-Employed 401(k) statement Q2 2026 (C:\WAN\K-G). Client: 52, single, WA, ~$700k W2, retiring in 2–3 years.
A4: Individual account value, 31 Jul 2026 | B4: =Holdings!E9 -> 2108781.9
A5: Stock options (intrinsic), 31 Jul 2026 | B5: ='Stock options'!G11 -> 1241001.8 | C5: Not in the brokerage account; stays at Fidelity Stock Plan Services
A6: Solo 401(k), 30 Jun 2026 | B6: ='Solo 401k & activity'!B9 -> 28717.97 | C6: All cash
A7: Total shown in the folder | B7: =B4+B5+B6 -> 3378501.7 | C7: Excludes $3.93M transferred to another Fidelity account in 2026 — statement not provided
A8: CHRW exposure (shares + options) | B8: ='Stock options'!G16 -> 2165053
A9: CHRW share of total | B9: ='Stock options'!G16/B7 -> 0.6408323 | C9: Plus salary from the same employer
A10: QQQ share of individual account | B10: =Holdings!L5 -> 0.54483743 | C10: Nasdaq-100: ~50% in ten technology companies
A11: Unrealized gains, individual account | B11: =Holdings!H9 -> 1426167.8
A12: Unrealized gain as % of positions | B12: =Holdings!I9 -> 0.68797471 | C12: Every $1 sold carries ~68¢ of taxable gain
A13: Tax if everything sold this year | B13: ='Tax scenarios'!G17 -> 424096.54 | C13: Federal 20% + NIIT 3.8% + WA 7–9.9%
A14: Tax per year if staged under WA exemption in retirement | B14: ='Tax scenarios'!G18 -> 41006.5 | C14: ~15% effective vs ~30%
A15: July 2026 change, account | B15: =Holdings!E11 -> -329507 | C15: −13.5%; CHRW −21.6%, QQQ −6.6%
A16: July 2026 change, options | B16: ='Stock options'!G22 -> 740970.06
A17: Estimated annual income | B17: =Holdings!J9 -> 20829.95 | C17: 1.0% yield
A18: Annual fund expense (QQQ) | B18: ='Fees & income'!B5 -> 2297.8866 | C18: No advisory fees

Sheet Holdings
A1: Fidelity Individual TOD X86-575950 — holdings at 31 Jul 2026
A2: Kollen Glynn · statement Jul 1–31 2026 · blue = transcribed, black = formula
A4: Symbol | B4: Security | C4: Quantity | D4: Price 7/31 | E4: Value 7/31 | F4: Value 7/1 | G4: Cost basis | H4: Unrealized | I4: Gain % of value | J4: Est. annual income | K4: Yield | L4: % of account
A5: QQQ | B5: Invesco QQQ Trust Series 1 | C5: 1670 | D5: 687.99 | E5: 1148943.3 | F5: 1229788 | G5: 179654.9 | H5: 969288.4 | I5: =H5/E5 -> 0.84363467 | J5: 5067.35 | K5: 0.0044 | L5: =E5/$E$9 -> 0.54483743
A6: CHRW | B6: C.H. Robinson Worldwide | C6: 6255 | D6: 147.73 | E6: 924051.15 | F6: 1178066.7 | G6: 467171.79 | H6: 456879.36 | I6: =H6/E6 -> 0.49443081 | J6: 15762.6 | K6: 0.0171 | L6: =E6/$E$9 -> 0.43819191
A7: CASH | B7: Core cash (free credit balance, 1.82%) | E7: 35787.42 | F7: 31362.44 | L7: =E7/$E$9 -> 0.01697066
B9: Account value (statement $2,108,781.87) | E9: =SUM(E5:E7) -> 2108781.9 | F9: =SUM(F5:F7) -> 2439217.1 | G9: =SUM(G5:G6) -> 646826.69 | H9: =SUM(H5:H6) -> 1426167.8 | I9: =H9/(E5+E6) -> 0.68797471 | J9: =SUM(J5:J6) -> 20829.95
B11: July change in investment value (statement −$329,507.00) | E11: =E9-F9-B23 -> -329507
B12: July return on beginning value | E12: =E11/F9 -> -0.13508719
B13: CHRW price change in July ($188.34 → $147.73) | E13: =147.73/188.34-1 -> -0.21562069
B14: QQQ price change in July | E14: =E5/F5-1 -> -0.065738729
A16: Account summary
A17: Beginning value, 1 Jan 2026 | B17: 6647397.3
A18: Transfers to other Fidelity accounts, YTD | B18: -3934184.8
A19: Deposits + exchanges in, YTD | B19: 1681.95
A20: Withdrawals + exchanges out, YTD | B20: -2889.54
A21: Change in investment value, YTD | B21: -603223.04
A22: Ending value 31 Jul 2026 | B22: =SUM(B17:B21) -> 2108781.9
A23: Net flows in July (deposits − withdrawals) | B23: -928.27
A24: Dividends + interest, July / YTD | B24: 5353.25
B25: 14715.04
A26: Stock-plan value (options, not in account), 1 Jul → 31 Jul | B26: 1981971.9
B27: 1241001.8
A28: Total incl. stock plan, 31 Jul | B28: =B22+B27 -> 3349783.7
A30: Note: the $3,934,185 moved to another Fidelity account during 2026 is not in the K-G folder; the YTD −$603,223 investment change is on the combined pre-transfer base, so a YTD return cannot be computed from this statement alone.

Sheet Stock options
A1: CHRW non-qualified stock options — Fidelity Stock Plan Services
A2: Values = (price − strike) × options. Change the price in B4 to see sensitivity.
A4: CHRW price | B4: 147.73
A5: Shares held in brokerage | B5: 6255
A7: Grant date | B7: Expiry | C7: Grant ID | D7: Type | E7: Strike | F7: Options | G7: Intrinsic value | H7: Value at $188.34 (7/1) | I7: Years to expiry
A8: 12/05/2018 | B8: 12/05/2028 | C8: SOPTS18 | D8: NSO | E8: 88.87 | F8: 2265 | G8: =MAX(0,$B$4-E8)*F8 -> 133317.9 | H8: =MAX(0,188.34-E8)*F8 -> 225299.55 | I8: =(DATEVALUE("12/05/2028")-DATE(2026,7,31))/365 -> 2.3506849
A9: 12/05/2018 | B9: 12/05/2028 | C9: SOPTS18 | D9: NSO | E9: 88.87 | F9: 5625 | G9: =MAX(0,$B$4-E9)*F9 -> 331087.5 | H9: =MAX(0,188.34-E9)*F9 -> 559518.75 | I9: =(DATEVALUE("12/05/2028")-DATE(2026,7,31))/365 -> 2.3506849
A10: 02/05/2020 | B10: 02/05/2030 | C10: SOPTS20 | D10: NSO (ISO disqualified, $100K rule) | E10: 72.74 | F10: 10356 | G10: =MAX(0,$B$4-E10)*F10 -> 776596.44 | H10: =MAX(0,188.34-E10)*F10 -> 1197153.6 | I10: =(DATEVALUE("02/05/2030")-DATE(2026,7,31))/365 -> 3.5205479
D11: Total (statement $1,241,001.84 / $1,981,971.90) | F11: =SUM(F8:F10) -> 18246 | G11: =SUM(G8:G10) -> 1241001.8 | H11: =SUM(H8:H10) -> 1981971.9
A13: CHRW exposure
A14: Shares in brokerage | G14: =B5*B4 -> 924051.15
A15: Options intrinsic value | G15: =G11 -> 1241001.8
A16: Total CHRW value | G16: =G14+G15 -> 2165053
A17: Total incl. options (Holdings!B28) | G17: =Holdings!B28 -> 3349783.7
A18: CHRW share of total wealth shown | G18: =G16/G17 -> 0.6463262
A19: Delta-equivalent shares (shares + in-the-money options) | G19: =B5+F11 -> 24501
A20: Notional CHRW exposure | G20: =G19*B4 -> 3619532.7
A21: Loss per $10 fall in CHRW | G21: =G19*10 -> 245010
A22: July loss on options (7/1 → 7/31) | G22: =H11-G11 -> 740970.06
A24: Ordinary-income tax on exercising all options today (federal 37% + 2.35% Medicare; no WA income tax) | G24: =G11*(0.37+0.0235) -> 488334.22

Sheet Tax scenarios
A1: Capital-gains tax on selling appreciated positions — 2026 parameters, single filer
A2: Yellow cells are assumptions; change them. Federal LTCG stacked on other income; NIIT 3.8% above $200k MAGI; WA capital-gains excise: 7% on gains above the exemption, 9.9% above $1M.
A4: Other taxable income while employed (W2) | B4: 700000
A5: Other taxable income in retirement (assumption) | B5: 20000
A6: Federal 0% LTCG ceiling (single, 2026) | B6: 49450
A7: Federal 15% LTCG ceiling (single, 2026) | B7: 545500
A8: NIIT threshold (single) | B8: 200000
A9: NIIT rate | B9: 0.038
A10: WA exemption (2025 indexed; 2026 not yet published) | B10: 278000
A11: WA rate, first $1M taxable | B11: 0.07
A12: WA rate above $1M | B12: 0.099
A14: Scenario | B14: Gain realised | C14: Other income | D14: Federal LTCG | E14: NIIT | F14: WA tax | G14: Total tax | H14: Effective rate | I14: Gain kept
A15: Sell all QQQ now | B15: =Holdings!H5 -> 969288.4 | C15: =B4 -> 700000 | D15: =MAX(0,MIN(C15+B15,$B$7)-MAX(C15,$B$6))*0.15+MAX(0,C15+B15-MAX(C15,$B$7))*0.2 -> 193857.68 | E15: =$B$9*MAX(0,MIN(B15,C15+B15-$B$8)) -> 36832.959 | F15: =MIN(MAX(0,B15-$B$10),1000000)*$B$11+MAX(0,B15-$B$10-1000000)*$B$12 -> 48390.188 | G15: =D15+E15+F15 -> 279080.83 | H15: =G15/B15 -> 0.28792342 | I15: =B15-G15 -> 690207.57
A16: Sell all CHRW now | B16: =Holdings!H6 -> 456879.36 | C16: =B4 -> 700000 | D16: =MAX(0,MIN(C16+B16,$B$7)-MAX(C16,$B$6))*0.15+MAX(0,C16+B16-MAX(C16,$B$7))*0.2 -> 91375.872 | E16: =$B$9*MAX(0,MIN(B16,C16+B16-$B$8)) -> 17361.416 | F16: =MIN(MAX(0,B16-$B$10),1000000)*$B$11+MAX(0,B16-$B$10-1000000)*$B$12 -> 12521.555 | G16: =D16+E16+F16 -> 121258.84 | H16: =G16/B16 -> 0.2654067 | I16: =B16-G16 -> 335620.52
A17: Sell both now | B17: =Holdings!H9 -> 1426167.8 | C17: =B4 -> 700000 | D17: =MAX(0,MIN(C17+B17,$B$7)-MAX(C17,$B$6))*0.15+MAX(0,C17+B17-MAX(C17,$B$7))*0.2 -> 285233.55 | E17: =$B$9*MAX(0,MIN(B17,C17+B17-$B$8)) -> 54194.375 | F17: =MIN(MAX(0,B17-$B$10),1000000)*$B$11+MAX(0,B17-$B$10-1000000)*$B$12 -> 84668.608 | G17: =D17+E17+F17 -> 424096.54 | H17: =G17/B17 -> 0.29736792 | I17: =B17-G17 -> 1002071.2
A18: Retired: realise gains up to WA exemption | B18: =B10 -> 278000 | C18: =B5 -> 20000 | D18: =MAX(0,MIN(C18+B18,$B$7)-MAX(C18,$B$6))*0.15+MAX(0,C18+B18-MAX(C18,$B$7))*0.2 -> 37282.5 | E18: =$B$9*MAX(0,MIN(B18,C18+B18-$B$8)) -> 3724 | F18: =MIN(MAX(0,B18-$B$10),1000000)*$B$11+MAX(0,B18-$B$10-1000000)*$B$12 -> 0 | G18: =D18+E18+F18 -> 41006.5 | H18: =G18/B18 -> 0.1475054 | I18: =B18-G18 -> 236993.5
A19: Retired: realise $400,000 | B19: 400000 | C19: =B5 -> 20000 | D19: =MAX(0,MIN(C19+B19,$B$7)-MAX(C19,$B$6))*0.15+MAX(0,C19+B19-MAX(C19,$B$7))*0.2 -> 55582.5 | E19: =$B$9*MAX(0,MIN(B19,C19+B19-$B$8)) -> 8360 | F19: =MIN(MAX(0,B19-$B$10),1000000)*$B$11+MAX(0,B19-$B$10-1000000)*$B$12 -> 8540 | G19: =D19+E19+F19 -> 72482.5 | H19: =G19/B19 -> 0.18120625 | I19: =B19-G19 -> 327517.5
A20: Retired: realise $545,500 (top of 15% band) | B20: =B7 -> 545500 | C20: =B5 -> 20000 | D20: =MAX(0,MIN(C20+B20,$B$7)-MAX(C20,$B$6))*0.15+MAX(0,C20+B20-MAX(C20,$B$7))*0.2 -> 78407.5 | E20: =$B$9*MAX(0,MIN(B20,C20+B20-$B$8)) -> 13889 | F20: =MIN(MAX(0,B20-$B$10),1000000)*$B$11+MAX(0,B20-$B$10-1000000)*$B$12 -> 18725 | G20: =D20+E20+F20 -> 111021.5 | H20: =G20/B20 -> 0.20352246 | I20: =B20-G20 -> 434478.5
A22: Federal ordinary-income bracket of 37% assumed already reached at $700k W2; LTCG brackets stack on top of ordinary income. NIIT applies to the lesser of the gain and MAGI above the threshold. WA tax ignores the charitable deduction (WA-based charities only, capped at $111k).

Sheet Unwind ladder
A1: Staged diversification — sell up to the WA exemption of gain each year after retirement
A2: Illustrative; prices held flat at 7/31/26. Yellow cells are levers. Sells CHRW first (single-stock risk, lower gain ratio), then QQQ.
A4: Gain budget per year | B4: 278000
A5: CHRW gain ratio (gain ÷ value) | B5: =Holdings!I6 -> 0.49443081
A6: QQQ gain ratio | B6: =Holdings!I5 -> 0.84363467
A7: Effective tax on gains realised in retirement (Tax scenarios row 18) | B7: ='Tax scenarios'!H18 -> 0.1475054
A9: Year | B9: CHRW value start | C9: QQQ value start | D9: CHRW sold | E9: QQQ sold | F9: Gain realised | G9: Tax (est.) | H9: Proceeds to diversify | I9: CHRW value end | J9: QQQ value end
A10: Year 1 | B10: =Holdings!E6 -> 924051.15 | C10: =Holdings!E5 -> 1148943.3 | D10: =MIN(B10,$B$4/$B$5) -> 562262.69 | E10: =MIN(C10,MAX(0,$B$4-D10*$B$5)/$B$6) -> 0 | F10: =D10*$B$5+E10*$B$6 -> 278000 | G10: =F10*$B$7 -> 41006.5 | H10: =D10+E10-G10 -> 521256.19 | I10: =B10-D10 -> 361788.46 | J10: =C10-E10 -> 1148943.3
A11: Year 2 | B11: =I10 -> 361788.46 | C11: =J10 -> 1148943.3 | D11: =MIN(B11,$B$4/$B$5) -> 361788.46 | E11: =MIN(C11,MAX(0,$B$4-D11*$B$5)/$B$6) -> 117492.37 | F11: =D11*$B$5+E11*$B$6 -> 278000 | G11: =F11*$B$7 -> 41006.5 | H11: =D11+E11-G11 -> 438274.33 | I11: =B11-D11 -> 0 | J11: =C11-E11 -> 1031450.9
A12: Year 3 | B12: =I11 -> 0 | C12: =J11 -> 1031450.9 | D12: =MIN(B12,$B$4/$B$5) -> 0 | E12: =MIN(C12,MAX(0,$B$4-D12*$B$5)/$B$6) -> 329526.52 | F12: =D12*$B$5+E12*$B$6 -> 278000 | G12: =F12*$B$7 -> 41006.5 | H12: =D12+E12-G12 -> 288520.02 | I12: =B12-D12 -> 0 | J12: =C12-E12 -> 701924.4
A13: Year 4 | B13: =I12 -> 0 | C13: =J12 -> 701924.4 | D13: =MIN(B13,$B$4/$B$5) -> 0 | E13: =MIN(C13,MAX(0,$B$4-D13*$B$5)/$B$6) -> 329526.52 | F13: =D13*$B$5+E13*$B$6 -> 278000 | G13: =F13*$B$7 -> 41006.5 | H13: =D13+E13-G13 -> 288520.02 | I13: =B13-D13 -> 0 | J13: =C13-E13 -> 372397.88
A14: Year 5 | B14: =I13 -> 0 | C14: =J13 -> 372397.88 | D14: =MIN(B14,$B$4/$B$5) -> 0 | E14: =MIN(C14,MAX(0,$B$4-D14*$B$5)/$B$6) -> 329526.52 | F14: =D14*$B$5+E14*$B$6 -> 278000 | G14: =F14*$B$7 -> 41006.5 | H14: =D14+E14-G14 -> 288520.02 | I14: =B14-D14 -> 0 | J14: =C14-E14 -> 42871.353
A15: Year 6 | B15: =I14 -> 0 | C15: =J14 -> 42871.353 | D15: =MIN(B15,$B$4/$B$5) -> 0 | E15: =MIN(C15,MAX(0,$B$4-D15*$B$5)/$B$6) -> 42871.353 | F15: =D15*$B$5+E15*$B$6 -> 36167.76 | G15: =F15*$B$7 -> 5334.9397 | H15: =D15+E15-G15 -> 37536.414 | I15: =B15-D15 -> 0 | J15: =C15-E15 -> 0
A17: Total | D17: =SUM(D10:D15) -> 924051.15 | E17: =SUM(E10:E15) -> 1148943.3 | F17: =SUM(F10:F15) -> 1426167.8 | G17: =SUM(G10:G15) -> 210367.44 | H17: =SUM(H10:H15) -> 1862627
A19: Compare: selling everything in one year while employed (Tax scenarios row 17) costs | G19: ='Tax scenarios'!G17 -> 424096.54
A20: Saving from staging (before time value and market movement) | G20: =G19-G17 -> 213729.1

Sheet Solo 401k & activity
A1: Self-Employed 401(k) 264-404076 (Whistler Ventures Inc) — Q2 2026
A2: 100% Fidelity Government Cash Reserves
A4: Beginning value 1 Apr 2026 | B4: 28479.6
A5: Contributions 2026 YTD | B5: 28333
A6: Money-fund dividends Q2 | B6: 238.37
A7: Ending value 30 Jun 2026 | B7: =B4+B6 -> 28717.97
A8: Est. annual income (money fund) | B8: 1051.6
A9: Value 30 Jun (statement $28,717.97) | B9: 28717.97
A11: Individual account — July 2026 activity
A12: Date | B12: Type | D12: Description | E12: Amount
A13: 07/01 | B13: Withdrawal | D13: Debit Elan web payment | E13: -947.21
A14: 07/02 | B14: Dividend | D14: CH Robinson Worldwide | E14: 3940.65
A15: 07/02 | B15: Deposit | D15: Elan Cardsvc redemption | E15: 18.94
A16: 07/10 | B16: Dividend | D16: Invesco QQQ Trust | E16: 1358.53
A17: 07/31 | B17: Interest | D17: Cash interest earned | E17: 54.07
D18: Net = change in core cash ($4,424.98) | E18: =SUM(E13:E17) -> 4424.98

Sheet Fees & income
A1: Fees and income
A2: No advisory fee on either account; costs are fund expenses and cash drag
A4: QQQ expense ratio (assumption) | B4: 0.002
A5: QQQ annual expense ($) | B5: =B4*Holdings!E5 -> 2297.8866
A6: Cash yield on Fidelity free credit balance | B6: 0.0182
A7: Cash interest earned per year at that rate | B7: =B6*Holdings!E7 -> 651.33104
A8: Money-market alternative yield (assumption) | B8: 0.04
A9: Foregone interest on brokerage cash | B9: =(B8-B6)*Holdings!E7 -> 780.16576
A10: Estimated annual dividends, individual account | B10: =Holdings!J9 -> 20829.95
A11: Portfolio yield | B11: =B10/Holdings!E9 -> 0.0098777168
A12: Fidelity outgoing ACATS fee | B12: 0
A13: Schwab incoming ACATS fee | B13: 0
